<DOMSymbolItem xmlns:xsi="http://www.w3.org/2001/XMLSchema-instance" xmlns="http://ns.adobe.com/xfl/2008/" name="Symbol 212" itemID="5c10919e-00000082" linkageExportForAS="true" linkageClassName="sliderTrack" lastModified="1544507382">
  <timeline>
    <DOMTimeline name="Symbol 212">
      <layers>
        <DOMLayer name="Labels Layer" color="#9FCB72">
          <frames>
            <DOMFrame index="0" name="up" labelType="name" keyMode="9728">
              <elements/>
            </DOMFrame>
            <DOMFrame index="1" duration="9" keyMode="9728">
              <elements/>
            </DOMFrame>
            <DOMFrame index="10" name="over" labelType="name" keyMode="9728">
              <elements/>
            </DOMFrame>
            <DOMFrame index="11" duration="9" keyMode="9728">
              <elements/>
            </DOMFrame>
            <DOMFrame index="20" name="down" labelType="name" keyMode="9728">
              <elements/>
            </DOMFrame>
            <DOMFrame index="21" duration="9" keyMode="9728">
              <elements/>
            </DOMFrame>
            <DOMFrame index="30" name="disabled" labelType="name" keyMode="9728">
              <elements/>
            </DOMFrame>
          </frames>
        </DOMLayer>
        <DOMLayer name="Layer 2" color="#38B893" current="true" isSelected="true">
          <frames>
            <DOMFrame index="0" duration="40" keyMode="9728">
              <elements>
                <DOMSymbolInstance libraryItemName="Symbol 211" centerPoint3DX="151" centerPoint3DY="21">
                  <transformationPoint>
                    <Point/>
                  </transformationPoint>
                </DOMSymbolInstance>
              </elements>
            </DOMFrame>
          </frames>
        </DOMLayer>
      </layers>
    </DOMTimeline>
  </timeline>
</DOMSymbolItem>